cppFileGenerator/__init__.py
cppfilegenerator-1.0.dist-info/licenses/LICENSE
cppfilegenerator-1.0.dist-info/METADATA
cppfilegenerator-1.0.dist-info/WHEEL
cppfilegenerator-1.0.dist-info/top_level.txt
cppfilegenerator-1.0.dist-info/RECORD
