Metadata-Version: 2.4
Name: cppFileGenerator
Version: 1.0
Summary: A Python tool to automatically generate C++ source and header files.
Author-email: weketlava <you@example.com>
License: MIT
Keywords: cpp,generator,header,source,automation
Classifier: Programming Language :: Python :: 3
Classifier: License :: OSI Approved :: MIT License
Classifier: Operating System :: OS Independent
Classifier: Topic :: Software Development :: Code Generators
Requires-Python: >=3.8
License-File: LICENSE
Dynamic: license-file
